torch_dreams/__init__.py
torch_dreams/auto_image_param.py
torch_dreams/batched_image_param.py
torch_dreams/batched_objective.py
torch_dreams/constants.py
torch_dreams/custom_image_param.py
torch_dreams/dreamer.py
torch_dreams/dreamer_utils.py
torch_dreams/error_handlers.py
torch_dreams/image_transforms.py
torch_dreams/losses.py
torch_dreams/masked_image_param.py
torch_dreams/model_bunch.py
torch_dreams/noisegrad.py
torch_dreams/transforms.py
torch_dreams/utils.py
torch_dreams/tests/__init__.py
torch_dreams/tests/test.py
torch_dreams/tests/test_batched.py
torch_dreams-4.0.0.dist-info/LICENSE
torch_dreams-4.0.0.dist-info/METADATA
torch_dreams-4.0.0.dist-info/WHEEL
torch_dreams-4.0.0.dist-info/top_level.txt
torch_dreams-4.0.0.dist-info/RECORD
