Metadata-Version: 2.1
Name: torch-dreams
Version: 4.0.0
Summary: Making neural networks more interpretable, for research and art
Home-page: https://github.com/Mayukhdeb/torch-dreams
Author: Mayukh Deb
Author-email: mayukhmainak2000@gmail.com
Keywords: PyTorch,machine learning,neural networks,convolutional neural networks,feature visualization,optimization
Classifier: Intended Audience :: Science/Research
Classifier: Intended Audience :: Education
Classifier: Natural Language :: English
Classifier: Programming Language :: Python :: 3.6
Classifier: Topic :: Scientific/Engineering
Classifier: Topic :: Scientific/Engineering :: Artificial Intelligence
Classifier: Topic :: Scientific/Engineering :: Mathematics
Classifier: Topic :: Scientific/Engineering :: Visualization
Classifier: Topic :: Software Development :: Libraries :: Python Modules
Requires-Python: >=3.6
License-File: LICENSE
Requires-Dist: torch (>=1.8.0)
Requires-Dist: torchvision (>=0.8.1)
Requires-Dist: opencv-python
Requires-Dist: numpy
Requires-Dist: tqdm
Requires-Dist: mkl
